pyK8sManager/DeploymentController.py
pyK8sManager/DeploymentManager.py
pyK8sManager/DescriptionGenerator.py
pyK8sManager/__init__.py
pyK8sManager-0.3.3.dist-info/LICENSE
pyK8sManager-0.3.3.dist-info/METADATA
pyK8sManager-0.3.3.dist-info/WHEEL
pyK8sManager-0.3.3.dist-info/top_level.txt
pyK8sManager-0.3.3.dist-info/RECORD
